indofaker/__init__.py
indofaker/language.py
indofaker/name/__init__.py
indofaker/name/base_name.py
indofaker/name/family_name.py
indofaker/name/first_name.py
indofaker/name/gender.py
indofaker/name/generate_name.py
indofaker/name/last_name.py
indofaker/name/middle_name.py
indofaker/name/religion.py
indofaker/name/tribe.py
indofaker-0.1.1.dist-info/METADATA
indofaker-0.1.1.dist-info/WHEEL
indofaker-0.1.1.dist-info/top_level.txt
indofaker-0.1.1.dist-info/RECORD
