Metadata-Version: 2.1
Name: indofaker
Version: 0.1.1
Summary: A Python library to generate fake data with Indonesian characteristics.
Home-page: https://github.com/firzaelbuho/indofaker
Author: Firza Aditya
Author-email: elbuho1315@gmail.com
Classifier: Programming Language :: Python :: 3
Classifier: License :: OSI Approved :: MIT License
Classifier: Operating System :: OS Independent
Requires-Python: >=3.6
